taxcalculatemounica/__init__.py
taxcalculatemounica/taxcal.py
taxcalculatemounica-0.1.dist-info/LICENCE
taxcalculatemounica-0.1.dist-info/METADATA
taxcalculatemounica-0.1.dist-info/WHEEL
taxcalculatemounica-0.1.dist-info/top_level.txt
taxcalculatemounica-0.1.dist-info/RECORD
